{
  "generated_utc": "2026-06-20T04:45:33Z",
  "top": [
    {
      "lon": 23.75,
      "lat": 37.75,
      "type": "hotspot_cell",
      "score": 26.495,
      "count": 67,
      "cell_deg": 0.5,
      "sources": {
        "GDELT": 66,
        "USGS": 0,
        "GDACS": 0,
        "RSS": 1
      },
      "last7_score": 21.992,
      "prev7_score": 4.503,
      "trend": "up",
      "trend_arrow": "🔺",
      "change_pct": 388.4,
      "place": "Regional Unit of East Attica, Greece"
    },
    {
      "lon": 19.25,
      "lat": 47.75,
      "type": "hotspot_cell",
      "score": 23.237,
      "count": 39,
      "cell_deg": 0.5,
      "sources": {
        "GDELT": 32,
        "USGS": 0,
        "GDACS": 0,
        "RSS": 7
      },
      "last7_score": 21.014,
      "prev7_score": 2.223,
      "trend": "up",
      "trend_arrow": "🔺",
      "change_pct": 845.4,
      "place": "Pest, Hungary"
    },
    {
      "lon": 22.25,
      "lat": 39.25,
      "type": "hotspot_cell",
      "score": 18.049,
      "count": 47,
      "cell_deg": 0.5,
      "sources": {
        "GDELT": 47,
        "USGS": 0,
        "GDACS": 0,
        "RSS": 0
      },
      "last7_score": 14.825,
      "prev7_score": 3.224,
      "trend": "up",
      "trend_arrow": "🔺",
      "change_pct": 359.8,
      "place": "Phthiotis Regional Unit, Greece"
    },
    {
      "lon": 25.25,
      "lat": 46.25,
      "type": "hotspot_cell",
      "score": 15.328,
      "count": 43,
      "cell_deg": 0.5,
      "sources": {
        "GDELT": 43,
        "USGS": 0,
        "GDACS": 0,
        "RSS": 0
      },
      "last7_score": 12.121,
      "prev7_score": 3.207,
      "trend": "up",
      "trend_arrow": "🔺",
      "change_pct": 278.0,
      "place": "Harghita, Romania"
    },
    {
      "lon": 20.25,
      "lat": 41.25,
      "type": "hotspot_cell",
      "score": 14.017,
      "count": 38,
      "cell_deg": 0.5,
      "sources": {
        "GDELT": 38,
        "USGS": 0,
        "GDACS": 0,
        "RSS": 0
      },
      "last7_score": 11.195,
      "prev7_score": 2.822,
      "trend": "up",
      "trend_arrow": "🔺",
      "change_pct": 296.6,
      "place": "Elbasan County, Albania"
    },
    {
      "lon": 20.25,
      "lat": 47.25,
      "type": "hotspot_cell",
      "score": 13.574,
      "count": 36,
      "cell_deg": 0.5,
      "sources": {
        "GDELT": 36,
        "USGS": 0,
        "GDACS": 0,
        "RSS": 0
      },
      "last7_score": 10.878,
      "prev7_score": 2.697,
      "trend": "up",
      "trend_arrow": "🔺",
      "change_pct": 303.4,
      "place": "Jász-Nagykun-Szolnok, Hungary"
    },
    {
      "lon": 27.25,
      "lat": 38.25,
      "type": "hotspot_cell",
      "score": 13.285,
      "count": 31,
      "cell_deg": 0.5,
      "sources": {
        "GDELT": 31,
        "USGS": 0,
        "GDACS": 0,
        "RSS": 0
      },
      "last7_score": 11.053,
      "prev7_score": 2.232,
      "trend": "up",
      "trend_arrow": "🔺",
      "change_pct": 395.1,
      "place": "Torbalı, Turkey"
    },
    {
      "lon": 26.25,
      "lat": 44.25,
      "type": "hotspot_cell",
      "score": 12.847,
      "count": 31,
      "cell_deg": 0.5,
      "sources": {
        "GDELT": 29,
        "USGS": 0,
        "GDACS": 0,
        "RSS": 2
      },
      "last7_score": 10.556,
      "prev7_score": 2.291,
      "trend": "up",
      "trend_arrow": "🔺",
      "change_pct": 360.8,
      "place": "Giurgiu, Romania"
    },
    {
      "lon": 25.25,
      "lat": 43.25,
      "type": "hotspot_cell",
      "score": 12.633,
      "count": 34,
      "cell_deg": 0.5,
      "sources": {
        "GDELT": 34,
        "USGS": 0,
        "GDACS": 0,
        "RSS": 0
      },
      "last7_score": 10.183,
      "prev7_score": 2.45,
      "trend": "up",
      "trend_arrow": "🔺",
      "change_pct": 315.6,
      "place": "Veliko Tarnovo, Bulgaria"
    },
    {
      "lon": 19.75,
      "lat": 41.25,
      "type": "hotspot_cell",
      "score": 12.247,
      "count": 32,
      "cell_deg": 0.5,
      "sources": {
        "GDELT": 31,
        "USGS": 0,
        "GDACS": 0,
        "RSS": 1
      },
      "last7_score": 9.802,
      "prev7_score": 2.445,
      "trend": "up",
      "trend_arrow": "🔺",
      "change_pct": 300.9,
      "place": "Tirana County, Albania"
    }
  ]
}