{
  "generated_utc": "2026-07-01T01:34:56Z",
  "top": [
    {
      "lon": 23.75,
      "lat": 37.75,
      "type": "hotspot_cell",
      "score": 28.734,
      "count": 68,
      "cell_deg": 0.5,
      "sources": {
        "GDELT": 66,
        "USGS": 0,
        "GDACS": 0,
        "RSS": 2
      },
      "last7_score": 24.232,
      "prev7_score": 4.502,
      "trend": "up",
      "trend_arrow": "🔺",
      "change_pct": 438.2,
      "place": "Regional Unit of East Attica, Greece"
    },
    {
      "lon": 19.25,
      "lat": 47.75,
      "type": "hotspot_cell",
      "score": 17.276,
      "count": 36,
      "cell_deg": 0.5,
      "sources": {
        "GDELT": 34,
        "USGS": 0,
        "GDACS": 0,
        "RSS": 2
      },
      "last7_score": 14.973,
      "prev7_score": 2.303,
      "trend": "up",
      "trend_arrow": "🔺",
      "change_pct": 550.2,
      "place": "Pest, Hungary"
    },
    {
      "lon": 22.25,
      "lat": 39.25,
      "type": "hotspot_cell",
      "score": 16.898,
      "count": 46,
      "cell_deg": 0.5,
      "sources": {
        "GDELT": 46,
        "USGS": 0,
        "GDACS": 0,
        "RSS": 0
      },
      "last7_score": 13.351,
      "prev7_score": 3.547,
      "trend": "up",
      "trend_arrow": "🔺",
      "change_pct": 276.4,
      "place": "Phthiotis Regional Unit, Greece"
    },
    {
      "lon": 19.75,
      "lat": 41.25,
      "type": "hotspot_cell",
      "score": 12.895,
      "count": 29,
      "cell_deg": 0.5,
      "sources": {
        "GDELT": 27,
        "USGS": 0,
        "GDACS": 0,
        "RSS": 2
      },
      "last7_score": 10.701,
      "prev7_score": 2.194,
      "trend": "up",
      "trend_arrow": "🔺",
      "change_pct": 387.8,
      "place": "Tirana County, Albania"
    },
    {
      "lon": 25.25,
      "lat": 46.25,
      "type": "hotspot_cell",
      "score": 12.407,
      "count": 35,
      "cell_deg": 0.5,
      "sources": {
        "GDELT": 35,
        "USGS": 0,
        "GDACS": 0,
        "RSS": 0
      },
      "last7_score": 9.637,
      "prev7_score": 2.771,
      "trend": "up",
      "trend_arrow": "🔺",
      "change_pct": 247.8,
      "place": "Harghita, Romania"
    },
    {
      "lon": 25.25,
      "lat": 43.25,
      "type": "hotspot_cell",
      "score": 11.894,
      "count": 31,
      "cell_deg": 0.5,
      "sources": {
        "GDELT": 31,
        "USGS": 0,
        "GDACS": 0,
        "RSS": 0
      },
      "last7_score": 9.449,
      "prev7_score": 2.445,
      "trend": "up",
      "trend_arrow": "🔺",
      "change_pct": 286.4,
      "place": "Veliko Tarnovo, Bulgaria"
    },
    {
      "lon": 20.25,
      "lat": 47.25,
      "type": "hotspot_cell",
      "score": 10.804,
      "count": 31,
      "cell_deg": 0.5,
      "sources": {
        "GDELT": 31,
        "USGS": 0,
        "GDACS": 0,
        "RSS": 0
      },
      "last7_score": 8.432,
      "prev7_score": 2.372,
      "trend": "up",
      "trend_arrow": "🔺",
      "change_pct": 255.5,
      "place": "Jász-Nagykun-Szolnok, Hungary"
    },
    {
      "lon": 26.25,
      "lat": 44.25,
      "type": "hotspot_cell",
      "score": 10.003,
      "count": 29,
      "cell_deg": 0.5,
      "sources": {
        "GDELT": 29,
        "USGS": 0,
        "GDACS": 0,
        "RSS": 0
      },
      "last7_score": 7.841,
      "prev7_score": 2.162,
      "trend": "up",
      "trend_arrow": "🔺",
      "change_pct": 262.7,
      "place": "Giurgiu, Romania"
    },
    {
      "lon": 27.25,
      "lat": 38.25,
      "type": "hotspot_cell",
      "score": 9.467,
      "count": 35,
      "cell_deg": 0.5,
      "sources": {
        "GDELT": 35,
        "USGS": 0,
        "GDACS": 0,
        "RSS": 0
      },
      "last7_score": 5.948,
      "prev7_score": 3.519,
      "trend": "up",
      "trend_arrow": "🔺",
      "change_pct": 69.0,
      "place": "Torbalı, Turkey"
    },
    {
      "lon": 18.25,
      "lat": 43.75,
      "type": "hotspot_cell",
      "score": 9.068,
      "count": 13,
      "cell_deg": 0.5,
      "sources": {
        "GDELT": 11,
        "USGS": 0,
        "GDACS": 0,
        "RSS": 2
      },
      "last7_score": 8.781,
      "prev7_score": 0.287,
      "trend": "up",
      "trend_arrow": "🔺",
      "change_pct": 2958.7,
      "place": "Federation of Bosnia and Herzegovina"
    }
  ]
}