{
  "generated_utc": "2026-07-17T11:43:19Z",
  "method_version": "risk_snapshot_v2_2_rss_integrated",
  "sources": {
    "gdelt_geo": true,
    "gdelt_linked": true,
    "gdacs": true,
    "usgs": true,
    "rss": true
  },
  "region": {
    "overall": "elevated",
    "overall_score": 1.119,
    "confidence": "medium",
    "confidence_value": 0.592,
    "dimensions": {
      "political": "elevated",
      "military": "normal",
      "policing": "normal",
      "migration": "normal",
      "social": "normal",
      "infrastructure": "normal"
    },
    "dimension_scores": {
      "political": 1.981,
      "military": 0.007,
      "policing": 0.005,
      "migration": 0.0,
      "social": 0.002,
      "infrastructure": 0.019
    },
    "watchlist": [
      {
        "country": "Greece",
        "overall": "elevated",
        "overall_score": 2.255,
        "drivers": [
          "unknown"
        ]
      },
      {
        "country": "Bulgaria",
        "overall": "elevated",
        "overall_score": 1.46,
        "drivers": [
          "unknown"
        ]
      },
      {
        "country": "Albania",
        "overall": "elevated",
        "overall_score": 1.411,
        "drivers": [
          "unknown"
        ]
      },
      {
        "country": "Turkey",
        "overall": "elevated",
        "overall_score": 1.203,
        "drivers": [
          "unknown"
        ]
      },
      {
        "country": "Bosnia and Herzegovina",
        "overall": "elevated",
        "overall_score": 0.978,
        "drivers": [
          "unknown"
        ]
      }
    ],
    "top_drivers": [
      "unknown",
      "explosion"
    ]
  },
  "countries": [
    {
      "country": "Greece",
      "overall": "elevated",
      "overall_score": 2.255,
      "confidence": "medium",
      "confidence_value": 0.591,
      "dimensions": {
        "political": "tense",
        "military": "normal",
        "policing": "normal",
        "migration": "normal",
        "social": "normal",
        "infrastructure": "normal"
      },
      "dimension_scores": {
        "political": 3.747,
        "military": 0.0,
        "policing": 0.07,
        "migration": 0.0,
        "social": 0.0,
        "infrastructure": 0.0
      },
      "drivers": [
        "unknown"
      ],
      "incident_count": 358,
      "recent_incident_count": 56,
      "top_incidents": [
        {
          "time": "2026-07-17T00:00:00Z",
          "title": "Greece",
          "event_type": "unknown",
          "score": 0.178,
          "source": "GDELT",
          "dimensions": [
            "political"
          ]
        },
        {
          "time": "2026-07-17T00:00:00Z",
          "title": "Athens, AttikíR, Greece",
          "event_type": "unknown",
          "score": 0.178,
          "source": "GDELT",
          "dimensions": [
            "political"
          ]
        },
        {
          "time": "2026-07-17T00:00:00Z",
          "title": "Greece",
          "event_type": "unknown",
          "score": 0.178,
          "source": "GDELT",
          "dimensions": [
            "political"
          ]
        },
        {
          "time": "2026-07-17T00:00:00Z",
          "title": "Greece",
          "event_type": "unknown",
          "score": 0.178,
          "source": "GDELT",
          "dimensions": [
            "political"
          ]
        },
        {
          "time": "2026-07-17T00:00:00Z",
          "title": "Athens, AttikíR, Greece",
          "event_type": "unknown",
          "score": 0.178,
          "source": "GDELT",
          "dimensions": [
            "political"
          ]
        }
      ]
    },
    {
      "country": "Romania",
      "overall": "normal",
      "overall_score": 1.752,
      "confidence": "medium",
      "confidence_value": 0.59,
      "dimensions": {
        "political": "tense",
        "military": "normal",
        "policing": "normal",
        "migration": "normal",
        "social": "normal",
        "infrastructure": "normal"
      },
      "dimension_scores": {
        "political": 3.026,
        "military": 0.0,
        "policing": 0.0,
        "migration": 0.0,
        "social": 0.0,
        "infrastructure": 0.0
      },
      "drivers": [
        "unknown"
      ],
      "incident_count": 160,
      "recent_incident_count": 23,
      "top_incidents": [
        {
          "time": "2026-07-17T00:00:00Z",
          "title": "Romania",
          "event_type": "unknown",
          "score": 0.178,
          "source": "GDELT",
          "dimensions": [
            "political"
          ]
        },
        {
          "time": "2026-07-17T00:00:00Z",
          "title": "Bucharest, Bucuresti, Romania",
          "event_type": "unknown",
          "score": 0.178,
          "source": "GDELT",
          "dimensions": [
            "political"
          ]
        },
        {
          "time": "2026-07-17T00:00:00Z",
          "title": "Romania",
          "event_type": "unknown",
          "score": 0.178,
          "source": "GDELT",
          "dimensions": [
            "political"
          ]
        },
        {
          "time": "2026-07-17T00:00:00Z",
          "title": "Cotroceni, Romania (general), Romania",
          "event_type": "unknown",
          "score": 0.178,
          "source": "GDELT",
          "dimensions": [
            "political"
          ]
        },
        {
          "time": "2026-07-17T00:00:00Z",
          "title": "Cluj, Cluj, Romania",
          "event_type": "unknown",
          "score": 0.178,
          "source": "GDELT",
          "dimensions": [
            "political"
          ]
        }
      ]
    },
    {
      "country": "Hungary",
      "overall": "normal",
      "overall_score": 1.49,
      "confidence": "medium",
      "confidence_value": 0.596,
      "dimensions": {
        "political": "tense",
        "military": "normal",
        "policing": "normal",
        "migration": "normal",
        "social": "normal",
        "infrastructure": "normal"
      },
      "dimension_scores": {
        "political": 2.617,
        "military": 0.018,
        "policing": 0.0,
        "migration": 0.0,
        "social": 0.018,
        "infrastructure": 0.018
      },
      "drivers": [
        "unknown"
      ],
      "incident_count": 100,
      "recent_incident_count": 15,
      "top_incidents": [
        {
          "time": "2026-07-17T00:00:00Z",
          "title": "Hungary",
          "event_type": "unknown",
          "score": 0.178,
          "source": "GDELT",
          "dimensions": [
            "political"
          ]
        },
        {
          "time": "2026-07-17T00:00:00Z",
          "title": "Budapest, Budapest, Hungary",
          "event_type": "unknown",
          "score": 0.178,
          "source": "GDELT",
          "dimensions": [
            "political"
          ]
        },
        {
          "time": "2026-07-17T00:00:00Z",
          "title": "Hungary",
          "event_type": "unknown",
          "score": 0.178,
          "source": "GDELT",
          "dimensions": [
            "political"
          ]
        },
        {
          "time": "2026-07-17T00:00:00Z",
          "title": "Szeged, Szeged, Hungary",
          "event_type": "unknown",
          "score": 0.178,
          "source": "GDELT",
          "dimensions": [
            "political"
          ]
        },
        {
          "time": "2026-07-17T00:00:00Z",
          "title": "Budapest, Budapest, Hungary",
          "event_type": "unknown",
          "score": 0.178,
          "source": "GDELT",
          "dimensions": [
            "political"
          ]
        }
      ]
    },
    {
      "country": "Bulgaria",
      "overall": "elevated",
      "overall_score": 1.46,
      "confidence": "medium",
      "confidence_value": 0.59,
      "dimensions": {
        "political": "elevated",
        "military": "normal",
        "policing": "normal",
        "migration": "normal",
        "social": "normal",
        "infrastructure": "normal"
      },
      "dimension_scores": {
        "political": 2.581,
        "military": 0.0,
        "policing": 0.0,
        "migration": 0.0,
        "social": 0.0,
        "infrastructure": 0.0
      },
      "drivers": [
        "unknown"
      ],
      "incident_count": 102,
      "recent_incident_count": 12,
      "top_incidents": [
        {
          "time": "2026-07-17T00:00:00Z",
          "title": "Sofia, Sofiya-Grad, Bulgaria",
          "event_type": "unknown",
          "score": 0.178,
          "source": "GDELT",
          "dimensions": [
            "political"
          ]
        },
        {
          "time": "2026-07-17T00:00:00Z",
          "title": "Sofia, Sofiya-Grad, Bulgaria",
          "event_type": "unknown",
          "score": 0.178,
          "source": "GDELT",
          "dimensions": [
            "political"
          ]
        },
        {
          "time": "2026-07-17T00:00:00Z",
          "title": "Bulgaria",
          "event_type": "unknown",
          "score": 0.178,
          "source": "GDELT",
          "dimensions": [
            "political"
          ]
        },
        {
          "time": "2026-07-17T00:00:00Z",
          "title": "Bulgaria",
          "event_type": "unknown",
          "score": 0.178,
          "source": "GDELT",
          "dimensions": [
            "political"
          ]
        },
        {
          "time": "2026-07-17T00:00:00Z",
          "title": "Sopot, Lovech, Bulgaria",
          "event_type": "unknown",
          "score": 0.178,
          "source": "GDELT",
          "dimensions": [
            "political"
          ]
        }
      ]
    },
    {
      "country": "Albania",
      "overall": "elevated",
      "overall_score": 1.411,
      "confidence": "medium",
      "confidence_value": 0.59,
      "dimensions": {
        "political": "elevated",
        "military": "normal",
        "policing": "normal",
        "migration": "normal",
        "social": "normal",
        "infrastructure": "normal"
      },
      "dimension_scores": {
        "political": 2.504,
        "military": 0.0,
        "policing": 0.0,
        "migration": 0.0,
        "social": 0.0,
        "infrastructure": 0.0
      },
      "drivers": [
        "unknown"
      ],
      "incident_count": 99,
      "recent_incident_count": 13,
      "top_incidents": [
        {
          "time": "2026-07-17T00:00:00Z",
          "title": "Tirana, Tirane, Albania",
          "event_type": "unknown",
          "score": 0.178,
          "source": "GDELT",
          "dimensions": [
            "political"
          ]
        },
        {
          "time": "2026-07-17T00:00:00Z",
          "title": "Zvernec, Vlore, Albania",
          "event_type": "unknown",
          "score": 0.178,
          "source": "GDELT",
          "dimensions": [
            "political"
          ]
        },
        {
          "time": "2026-07-17T00:00:00Z",
          "title": "Albania",
          "event_type": "unknown",
          "score": 0.178,
          "source": "GDELT",
          "dimensions": [
            "political"
          ]
        },
        {
          "time": "2026-07-17T00:00:00Z",
          "title": "Tirana, Tirane, Albania",
          "event_type": "unknown",
          "score": 0.178,
          "source": "GDELT",
          "dimensions": [
            "political"
          ]
        },
        {
          "time": "2026-07-16T00:00:00Z",
          "title": "Albania",
          "event_type": "unknown",
          "score": 0.125,
          "source": "GDELT",
          "dimensions": [
            "political"
          ]
        }
      ]
    },
    {
      "country": "Turkey",
      "overall": "elevated",
      "overall_score": 1.203,
      "confidence": "medium",
      "confidence_value": 0.59,
      "dimensions": {
        "political": "elevated",
        "military": "normal",
        "policing": "normal",
        "migration": "normal",
        "social": "normal",
        "infrastructure": "normal"
      },
      "dimension_scores": {
        "political": 2.17,
        "military": 0.0,
        "policing": 0.0,
        "migration": 0.0,
        "social": 0.0,
        "infrastructure": 0.0
      },
      "drivers": [
        "unknown"
      ],
      "incident_count": 83,
      "recent_incident_count": 5,
      "top_incidents": [
        {
          "time": "2026-07-16T00:00:00Z",
          "title": "Smyrna, Izmir, Turkey",
          "event_type": "unknown",
          "score": 0.125,
          "source": "GDELT",
          "dimensions": [
            "political"
          ]
        },
        {
          "time": "2026-07-16T00:00:00Z",
          "title": "Midia, Kirklareli, Turkey",
          "event_type": "unknown",
          "score": 0.125,
          "source": "GDELT",
          "dimensions": [
            "political"
          ]
        },
        {
          "time": "2026-07-16T00:00:00Z",
          "title": "Azmir, Izmir, Turkey",
          "event_type": "unknown",
          "score": 0.125,
          "source": "GDELT",
          "dimensions": [
            "political"
          ]
        },
        {
          "time": "2026-07-16T00:00:00Z",
          "title": "Bursa, Bursa, Turkey",
          "event_type": "unknown",
          "score": 0.125,
          "source": "GDELT",
          "dimensions": [
            "political"
          ]
        },
        {
          "time": "2026-07-16T00:00:00Z",
          "title": "Heybeliada, Istanbul, Turkey",
          "event_type": "unknown",
          "score": 0.125,
          "source": "GDELT",
          "dimensions": [
            "political"
          ]
        }
      ]
    },
    {
      "country": "Bosnia and Herzegovina",
      "overall": "elevated",
      "overall_score": 0.978,
      "confidence": "medium",
      "confidence_value": 0.59,
      "dimensions": {
        "political": "elevated",
        "military": "normal",
        "policing": "normal",
        "migration": "normal",
        "social": "normal",
        "infrastructure": "normal"
      },
      "dimension_scores": {
        "political": 1.797,
        "military": 0.0,
        "policing": 0.0,
        "migration": 0.0,
        "social": 0.0,
        "infrastructure": 0.0
      },
      "drivers": [
        "unknown"
      ],
      "incident_count": 49,
      "recent_incident_count": 6,
      "top_incidents": [
        {
          "time": "2026-07-17T00:00:00Z",
          "title": "Skocic, Republika Srpska, Bosnia-Herzegovina",
          "event_type": "unknown",
          "score": 0.21,
          "source": "GDELT",
          "dimensions": [
            "political"
          ]
        },
        {
          "time": "2026-07-17T00:00:00Z",
          "title": "Srebrenica, Republika Srpska, Bosnia-Herzegovina",
          "event_type": "unknown",
          "score": 0.21,
          "source": "GDELT",
          "dimensions": [
            "political"
          ]
        },
        {
          "time": "2026-07-17T00:00:00Z",
          "title": "Sarajevo, Federation of Bosnia and Herzegovina, Bosnia-Herzegovina",
          "event_type": "unknown",
          "score": 0.182,
          "source": "GDELT",
          "dimensions": [
            "political"
          ]
        },
        {
          "time": "2026-07-16T00:00:00Z",
          "title": "Srebrenica, Republika Srpska, Bosnia-Herzegovina",
          "event_type": "unknown",
          "score": 0.149,
          "source": "GDELT",
          "dimensions": [
            "political"
          ]
        },
        {
          "time": "2026-07-16T00:00:00Z",
          "title": "Maglaj, Federation of Bosnia and Herzegovina, Bosnia-Herzegovina",
          "event_type": "unknown",
          "score": 0.129,
          "source": "GDELT",
          "dimensions": [
            "political"
          ]
        }
      ]
    },
    {
      "country": "Croatia",
      "overall": "elevated",
      "overall_score": 0.908,
      "confidence": "medium",
      "confidence_value": 0.59,
      "dimensions": {
        "political": "elevated",
        "military": "normal",
        "policing": "normal",
        "migration": "normal",
        "social": "normal",
        "infrastructure": "normal"
      },
      "dimension_scores": {
        "political": 1.679,
        "military": 0.0,
        "policing": 0.0,
        "migration": 0.0,
        "social": 0.0,
        "infrastructure": 0.0
      },
      "drivers": [
        "unknown"
      ],
      "incident_count": 49,
      "recent_incident_count": 4,
      "top_incidents": [
        {
          "time": "2026-07-17T00:00:00Z",
          "title": "Croatia",
          "event_type": "unknown",
          "score": 0.178,
          "source": "GDELT",
          "dimensions": [
            "political"
          ]
        },
        {
          "time": "2026-07-17T00:00:00Z",
          "title": "Zagreb, Zagreb, Grad, Croatia",
          "event_type": "unknown",
          "score": 0.178,
          "source": "GDELT",
          "dimensions": [
            "political"
          ]
        },
        {
          "time": "2026-07-16T00:00:00Z",
          "title": "Croatia",
          "event_type": "unknown",
          "score": 0.125,
          "source": "GDELT",
          "dimensions": [
            "political"
          ]
        },
        {
          "time": "2026-07-16T00:00:00Z",
          "title": "Croatia",
          "event_type": "unknown",
          "score": 0.125,
          "source": "GDELT",
          "dimensions": [
            "political"
          ]
        },
        {
          "time": "2026-07-15T00:00:00Z",
          "title": "Croatia",
          "event_type": "unknown",
          "score": 0.125,
          "source": "GDELT",
          "dimensions": [
            "political"
          ]
        }
      ]
    },
    {
      "country": "Moldova",
      "overall": "elevated",
      "overall_score": 0.81,
      "confidence": "medium",
      "confidence_value": 0.59,
      "dimensions": {
        "political": "elevated",
        "military": "normal",
        "policing": "normal",
        "migration": "normal",
        "social": "normal",
        "infrastructure": "normal"
      },
      "dimension_scores": {
        "political": 1.51,
        "military": 0.0,
        "policing": 0.0,
        "migration": 0.0,
        "social": 0.0,
        "infrastructure": 0.0
      },
      "drivers": [
        "unknown"
      ],
      "incident_count": 40,
      "recent_incident_count": 3,
      "top_incidents": [
        {
          "time": "2026-07-17T00:00:00Z",
          "title": "Moldova",
          "event_type": "unknown",
          "score": 0.178,
          "source": "GDELT",
          "dimensions": [
            "political"
          ]
        },
        {
          "time": "2026-07-16T00:00:00Z",
          "title": "Moldova",
          "event_type": "unknown",
          "score": 0.125,
          "source": "GDELT",
          "dimensions": [
            "political"
          ]
        },
        {
          "time": "2026-07-16T00:00:00Z",
          "title": "Chisinau, Chisinau, Moldova",
          "event_type": "unknown",
          "score": 0.125,
          "source": "GDELT",
          "dimensions": [
            "political"
          ]
        },
        {
          "time": "2026-07-15T00:00:00Z",
          "title": "Moldova",
          "event_type": "unknown",
          "score": 0.125,
          "source": "GDELT",
          "dimensions": [
            "political"
          ]
        },
        {
          "time": "2026-07-15T00:00:00Z",
          "title": "Moldova",
          "event_type": "unknown",
          "score": 0.125,
          "source": "GDELT",
          "dimensions": [
            "political"
          ]
        }
      ]
    },
    {
      "country": "Slovenia",
      "overall": "elevated",
      "overall_score": 0.762,
      "confidence": "medium",
      "confidence_value": 0.59,
      "dimensions": {
        "political": "elevated",
        "military": "normal",
        "policing": "normal",
        "migration": "normal",
        "social": "normal",
        "infrastructure": "normal"
      },
      "dimension_scores": {
        "political": 1.426,
        "military": 0.0,
        "policing": 0.0,
        "migration": 0.0,
        "social": 0.0,
        "infrastructure": 0.0
      },
      "drivers": [
        "unknown"
      ],
      "incident_count": 28,
      "recent_incident_count": 7,
      "top_incidents": [
        {
          "time": "2026-07-17T00:00:00Z",
          "title": "Slovenia",
          "event_type": "unknown",
          "score": 0.178,
          "source": "GDELT",
          "dimensions": [
            "political"
          ]
        },
        {
          "time": "2026-07-17T00:00:00Z",
          "title": "Ljubljana, Slovenia (general), Slovenia",
          "event_type": "unknown",
          "score": 0.178,
          "source": "GDELT",
          "dimensions": [
            "political"
          ]
        },
        {
          "time": "2026-07-17T00:00:00Z",
          "title": "Slovenia",
          "event_type": "unknown",
          "score": 0.178,
          "source": "GDELT",
          "dimensions": [
            "political"
          ]
        },
        {
          "time": "2026-07-17T00:00:00Z",
          "title": "Ljubljana, Slovenia (general), Slovenia",
          "event_type": "unknown",
          "score": 0.178,
          "source": "GDELT",
          "dimensions": [
            "political"
          ]
        },
        {
          "time": "2026-07-16T00:00:00Z",
          "title": "Slovenia",
          "event_type": "unknown",
          "score": 0.125,
          "source": "GDELT",
          "dimensions": [
            "political"
          ]
        }
      ]
    },
    {
      "country": "Montenegro",
      "overall": "elevated",
      "overall_score": 0.711,
      "confidence": "medium",
      "confidence_value": 0.615,
      "dimensions": {
        "political": "elevated",
        "military": "normal",
        "policing": "normal",
        "migration": "normal",
        "social": "normal",
        "infrastructure": "normal"
      },
      "dimension_scores": {
        "political": 1.16,
        "military": 0.079,
        "policing": 0.0,
        "migration": 0.0,
        "social": 0.014,
        "infrastructure": 0.23
      },
      "drivers": [
        "unknown",
        "explosion"
      ],
      "incident_count": 33,
      "recent_incident_count": 5,
      "top_incidents": [
        {
          "time": "2026-07-17T11:05:11Z",
          "title": "First Thing: Trump launches wide-ranging and unverified attack on integrity of US electoral system",
          "event_type": "explosion",
          "score": 0.38,
          "source": "RSS",
          "dimensions": [
            "political",
            "infrastructure"
          ]
        },
        {
          "time": "2026-07-16T00:00:00Z",
          "title": "Montenegro",
          "event_type": "unknown",
          "score": 0.125,
          "source": "GDELT",
          "dimensions": [
            "political"
          ]
        },
        {
          "time": "2026-07-16T00:00:00Z",
          "title": "Montenegro",
          "event_type": "unknown",
          "score": 0.125,
          "source": "GDELT",
          "dimensions": [
            "political"
          ]
        },
        {
          "time": "2026-07-15T00:00:00Z",
          "title": "Montenegro",
          "event_type": "unknown",
          "score": 0.125,
          "source": "GDELT",
          "dimensions": [
            "political"
          ]
        },
        {
          "time": "2026-07-15T00:00:00Z",
          "title": "Montenegro",
          "event_type": "unknown",
          "score": 0.125,
          "source": "GDELT",
          "dimensions": [
            "political"
          ]
        }
      ]
    },
    {
      "country": "Kosovo",
      "overall": "elevated",
      "overall_score": 0.649,
      "confidence": "medium",
      "confidence_value": 0.59,
      "dimensions": {
        "political": "elevated",
        "military": "normal",
        "policing": "normal",
        "migration": "normal",
        "social": "normal",
        "infrastructure": "normal"
      },
      "dimension_scores": {
        "political": 1.226,
        "military": 0.0,
        "policing": 0.0,
        "migration": 0.0,
        "social": 0.0,
        "infrastructure": 0.0
      },
      "drivers": [
        "unknown"
      ],
      "incident_count": 29,
      "recent_incident_count": 4,
      "top_incidents": [
        {
          "time": "2026-07-17T00:00:00Z",
          "title": "Kosovo",
          "event_type": "unknown",
          "score": 0.178,
          "source": "GDELT",
          "dimensions": [
            "political"
          ]
        },
        {
          "time": "2026-07-17T00:00:00Z",
          "title": "Kosovo",
          "event_type": "unknown",
          "score": 0.178,
          "source": "GDELT",
          "dimensions": [
            "political"
          ]
        },
        {
          "time": "2026-07-16T00:00:00Z",
          "title": "Kosovo",
          "event_type": "unknown",
          "score": 0.125,
          "source": "GDELT",
          "dimensions": [
            "political"
          ]
        },
        {
          "time": "2026-07-16T00:00:00Z",
          "title": "Kosovo",
          "event_type": "unknown",
          "score": 0.125,
          "source": "GDELT",
          "dimensions": [
            "political"
          ]
        },
        {
          "time": "2026-07-15T00:00:00Z",
          "title": "Peja, Opstina Pec, Kosovo",
          "event_type": "unknown",
          "score": 0.125,
          "source": "GDELT",
          "dimensions": [
            "political"
          ]
        }
      ]
    },
    {
      "country": "Serbia",
      "overall": "normal",
      "overall_score": 0.155,
      "confidence": "medium",
      "confidence_value": 0.59,
      "dimensions": {
        "political": "normal",
        "military": "normal",
        "policing": "normal",
        "migration": "normal",
        "social": "normal",
        "infrastructure": "normal"
      },
      "dimension_scores": {
        "political": 0.306,
        "military": 0.0,
        "policing": 0.0,
        "migration": 0.0,
        "social": 0.0,
        "infrastructure": 0.0
      },
      "drivers": [
        "unknown"
      ],
      "incident_count": 3,
      "recent_incident_count": 2,
      "top_incidents": [
        {
          "time": "2026-07-17T00:00:00Z",
          "title": "Iron Gates, , Serbia",
          "event_type": "unknown",
          "score": 0.178,
          "source": "GDELT",
          "dimensions": [
            "political"
          ]
        },
        {
          "time": "2026-07-16T00:00:00Z",
          "title": "Djerdap, , Serbia",
          "event_type": "unknown",
          "score": 0.125,
          "source": "GDELT",
          "dimensions": [
            "political"
          ]
        },
        {
          "time": "2026-07-09T00:00:00Z",
          "title": "Ivica, , Serbia",
          "event_type": "unknown",
          "score": 0.025,
          "source": "GDELT",
          "dimensions": [
            "political"
          ]
        }
      ]
    },
    {
      "country": "North Macedonia",
      "overall": "normal",
      "overall_score": 0.0,
      "confidence": "low",
      "confidence_value": 0.0,
      "dimensions": {
        "political": "normal",
        "military": "normal",
        "policing": "normal",
        "migration": "normal",
        "social": "normal",
        "infrastructure": "normal"
      },
      "dimension_scores": {
        "political": 0.0,
        "military": 0.0,
        "policing": 0.0,
        "migration": 0.0,
        "social": 0.0,
        "infrastructure": 0.0
      },
      "drivers": [],
      "incident_count": 0,
      "recent_incident_count": 0,
      "top_incidents": []
    }
  ],
  "stats": {
    "incident_count": 1140,
    "country_count": 14,
    "active_country_count": 13,
    "rss_story_count_raw": 126
  },
  "legend": {
    "levels": [
      "normal",
      "elevated",
      "tense",
      "critical"
    ],
    "dimensions": [
      "political",
      "military",
      "policing",
      "migration",
      "social",
      "infrastructure"
    ],
    "confidence": [
      "low",
      "medium",
      "high"
    ]
  }
}