{
  "generated_utc": "2026-06-19T16:16:48Z",
  "headline": "Balkán biztonsági helyzet – napi kivonat",
  "bullets": [
    "Napi kiemelt fejlemény: Montenegro – Costa on list of ‘undesirables’ targeted by Portuguese neo-Nazi group (Politico Europe)",
    "Legerősebb góc: Regional Unit of East Attica, Greece (score 28.38)",
    "Trend: emelkedő (+397%).",
    "Forráskép: GDELT 0 + linked 1213, USGS 0, GDACS 1, RSS-jelek 24",
    "Trusted RSS: 90 db",
    "Automatikus OSINT kivonat."
  ],
  "alert": {
    "level": "high",
    "title": "Napi kiemelt fejlemény – Montenegro",
    "text": "Costa on list of ‘undesirables’ targeted by Portuguese neo-Nazi group"
  },
  "stats": {
    "score_last7": 405.771,
    "score_prev7": 81.588,
    "change_pct": 397.34
  },
  "rss_count": 90
}