{
  "generated_utc": "2026-04-21T19:40:18Z",
  "headline": "Balkán biztonsági helyzet – napi kivonat",
  "bullets": [
    "Napi kiemelt fejlemény: Albania – Albanians are being unfairly demonised in illegal immigration debate | Letter (The Guardian Europe)",
    "Legerősebb góc: Pest, Hungary (score 41.30)",
    "Trend: emelkedő (+505%).",
    "Forráskép: GDELT 0 + linked 1164, USGS 0, GDACS 0, RSS-jelek 34",
    "Trusted RSS: 130 db",
    "Automatikus OSINT kivonat."
  ],
  "alert": {
    "level": "high",
    "title": "Napi kiemelt fejlemény – Albania",
    "text": "Albanians are being unfairly demonised in illegal immigration debate | Letter"
  },
  "stats": {
    "score_last7": 411.866,
    "score_prev7": 68.03,
    "change_pct": 505.42
  },
  "rss_count": 130
}