{
  "generated_utc": "2026-07-09T12:18:41Z",
  "headline": "Balkán biztonsági helyzet – napi kivonat",
  "bullets": [
    "Napi kiemelt fejlemény: Bosnia and Herzegovina – Thousands embark on Bosnia peace march to remember Srebrenica victims (Euronews)",
    "Legerősebb góc: Gölbaşı, Turkey (score 84.58)",
    "Trend: emelkedő (+460%).",
    "Forráskép: GDELT 0 + linked 1134, USGS 0, GDACS 0, RSS-jelek 70",
    "Trusted RSS: 134 db",
    "Automatikus OSINT kivonat."
  ],
  "alert": {
    "level": "info",
    "title": "Napi kiemelt fejlemény – Bosnia and Herzegovina",
    "text": "Thousands embark on Bosnia peace march to remember Srebrenica victims"
  },
  "stats": {
    "score_last7": 453.098,
    "score_prev7": 80.924,
    "change_pct": 459.9
  },
  "rss_count": 134
}