{
  "generated_utc": "2026-04-26T23:59:05Z",
  "headline": "Balkán biztonsági helyzet – napi kivonat",
  "bullets": [
    "Legerősebb góc: Regional Unit of East Attica, Greece (score 37.68)",
    "Trend: emelkedő (+457%).",
    "Forráskép: GDELT 0 + linked 1192, USGS 0, GDACS 0, RSS-jelek 24",
    "Trusted RSS: 132 db",
    "Automatikus OSINT kivonat."
  ],
  "alert": {
    "level": "high",
    "title": "Emelkedő feszültség",
    "text": "Erősödő hotspot: Regional Unit of East Attica, Greece (+719%)."
  },
  "stats": {
    "score_last7": 348.328,
    "score_prev7": 62.53,
    "change_pct": 457.06
  },
  "rss_count": 132
}